{"AboutText":{"id":"AboutText","value":"Telif hakkı &copy; {0} Infor. Tüm hakları saklıdır. Bu belgede belirtilen marka isimleri ve tasarımları, Infor ve/veya bağlı şirketleri ve iştiraklerinin ticari markaları ve/veya tescilli ticari markalarıdır. Burada belirtilen diğer tüm ticari markalar ilgili sahiplerinin mülkiyetindedir"},"Actions":{"id":"Actions","value":"Eylemler"},"Add":{"id":"Add","value":"Ekle"},"AddComments":{"id":"AddComments","value":"Yorumlar ekle"},"AddNewTab":{"id":"AddNewTab","value":"Yeni sekme ekle"},"AdministrativeLeave":{"id":"AdministrativeLeave","value":"Yönetimden ayrılma"},"AdvancedFilter":{"id":"AdvancedFilter","value":"Gelişmiş filtre oluştur"},"Afrikaans":{"id":"Afrikaans","value":"Afrikanca"},"Alabaster":{"id":"Alabaster","value":"Alabaster"},"Alert":{"id":"Alert","value":"Uyarı"},"AlertOnPage":{"id":"AlertOnPage","value":"Sayfada mesaj uyarısı ver"},"AlignCenterHorizontally":{"id":"AlignCenterHorizontally","value":"Yatay hizalama orta"},"AligntoBottom":{"id":"AligntoBottom","value":"Alta hizala"},"All":{"id":"All","value":"Hepsi"},"AllDay":{"id":"AllDay","value":"Tüm gün"},"AllResults":{"id":"AllResults","value":"Şunun için tüm sonuçlar:"},"Amber":{"id":"Amber","value":"Kehribar"},"Amethyst":{"id":"Amethyst","value":"Ametist"},"And":{"id":"And","value":"ve"},"AppMenuTriggerText":{"id":"AppMenuTriggerText","value":"Menü"},"AppMenuTriggerTextAlt":{"id":"AppMenuTriggerTextAlt","value":"Uygulama menüsü tetikleyici"},"Apply":{"id":"Apply","value":"Uygula"},"Arabic":{"id":"Arabic","value":"Arapça"},"Attach":{"id":"Attach","value":"Ekle"},"Available":{"id":"Available","value":"Mevcut"},"Azure":{"id":"Azure","value":"Lacivert taşı"},"BackgroundColor":{"id":"BackgroundColor","value":"Arka plan rengi"},"BarChart":{"id":"BarChart","value":"Çubuk Çizelge"},"Between":{"id":"Between","value":"Arasında"},"BillionsAbbrev":{"id":"BillionsAbbrev","value":"{0}b"},"Blockquote":{"id":"Blockquote","value":"Alıntı kısmı"},"Bold":{"id":"Bold","value":"Kalın"},"BookmarkThis":{"id":"BookmarkThis","value":"Buna yer işareti ekle"},"Bookmarked":{"id":"Bookmarked","value":"Yer işareti eklendi"},"Breadcrumb":{"id":"Breadcrumb","value":"İçerik haritası"},"Browser":{"id":"Browser","value":"Tarayıcı"},"BrowserLanguage":{"id":"BrowserLanguage","value":"Tarayıcı dili"},"Bulgarian":{"id":"Bulgarian","value":"Bulgarca"},"BulletedList":{"id":"BulletedList","value":"Madde işaretli liste"},"Calendar":{"id":"Calendar","value":"Takvim"},"Camera":{"id":"Camera","value":"Kamera"},"Cancel":{"id":"Cancel","value":"İptal"},"CapsLockOn":{"id":"CapsLockOn","value":"Caps lock açık"},"Cart":{"id":"Cart","value":"Alışveriş sepeti"},"CenterText":{"id":"CenterText","value":"Ortala"},"ChangeSelection":{"id":"ChangeSelection","value":"Seçilen öğeyi değiştirmek için ok tuşlarını kullanın."},"ChangeView":{"id":"ChangeView","value":"Görünümü değiştir"},"CharactersLeft":{"id":"CharactersLeft","value":"Kalan karakter {0}"},"CharactersMax":{"id":"CharactersMax","value":"Maksimum karakter sayısı "},"Checkbox":{"id":"Checkbox","value":"Onay kutusu"},"Checked":{"id":"Checked","value":"İşaretli"},"Chinese":{"id":"Chinese","value":"Çince"},"ChooseFont":{"id":"ChooseFont","value":"Yazı tipi stili seç"},"Classic":{"id":"Classic","value":"Klasik"},"ClassicDarkTheme":{"id":"ClassicDarkTheme","value":"Klasik karanlık"},"ClassicHighContrastTheme":{"id":"ClassicHighContrastTheme","value":"Klasik yüksek kontrast"},"ClassicLightTheme":{"id":"ClassicLightTheme","value":"Klasik aydınlık"},"Clear":{"id":"Clear","value":"Temizle"},"ClearFilter":{"id":"ClearFilter","value":"Filtreyi temizle"},"ClearFormatting":{"id":"ClearFormatting","value":"Biçimlendirmeyi temizle"},"ClearSelection":{"id":"ClearSelection","value":"(Seçimi Kaldır)"},"Clickable":{"id":"Clickable","value":"Düzenleyici kısmında tıklanabilir"},"Clock":{"id":"Clock","value":"Saat"},"Close":{"id":"Close","value":"Kapat"},"Collapse":{"id":"Collapse","value":"Daralt"},"CollapseAppTray":{"id":"CollapseAppTray","value":"Uygulama tepsisini daralt"},"Color":{"id":"Color","value":"Renk"},"ColorPickerSelection":{"id":"ColorPickerSelection","value":"Özel bir renk seç"},"ColorPickerTriggerButton":{"id":"ColorPickerTriggerButton","value":"Renk seçiciyi açmak için tıklayın"},"Colors":{"id":"Colors","value":"Renkler"},"Columns":{"id":"Columns","value":"Sütunlar"},"Comments":{"id":"Comments","value":"Yorumlar"},"CompanyHoliday":{"id":"CompanyHoliday","value":"Şirket tatili"},"Completed":{"id":"Completed","value":"Tamamlandı"},"Component":{"id":"Component","value":"Bileşen"},"Compose":{"id":"Compose","value":"Oluştur"},"Confirm":{"id":"Confirm","value":"Onayla"},"ConfirmOnPage":{"id":"ConfirmOnPage","value":"Sayfada mesajları onayla"},"Contains":{"id":"Contains","value":"Şunu İçerir"},"Contrast":{"id":"Contrast","value":"Kontrast"},"CookiesEnabled":{"id":"CookiesEnabled","value":"Tanımlama bilgileri etkin"},"Copy":{"id":"Copy","value":"Kopyala"},"Croatian":{"id":"Croatian","value":"Hırvatça"},"CssClass":{"id":"CssClass","value":"Css sınıfı"},"Cut":{"id":"Cut","value":"Kes"},"Czech":{"id":"Czech","value":"Çekçe"},"Danish":{"id":"Danish","value":"Danca"},"Dark":{"id":"Dark","value":"Karanlık"},"Datagrid":{"id":"Datagrid","value":"Veri Kılavuzu"},"Date":{"id":"Date","value":"Tarih"},"DatePickerTriggerButton":{"id":"DatePickerTriggerButton","value":"Tarih seçici tetikleyici"},"Day":{"id":"Day","value":"Gün"},"DayAbbreviatedFri":{"id":"DayAbbreviatedFri","value":"Cum"},"DayAbbreviatedMon":{"id":"DayAbbreviatedMon","value":"Pzt"},"DayAbbreviatedSat":{"id":"DayAbbreviatedSat","value":"Cts"},"DayAbbreviatedSun":{"id":"DayAbbreviatedSun","value":"Pzr"},"DayAbbreviatedThu":{"id":"DayAbbreviatedThu","value":"Per"},"DayAbbreviatedTue":{"id":"DayAbbreviatedTue","value":"Sal"},"DayAbbreviatedWed":{"id":"DayAbbreviatedWed","value":"Çar"},"DayNarrowFri":{"id":"DayNarrowFri","value":"C"},"DayNarrowMon":{"id":"DayNarrowMon","value":"P"},"DayNarrowSat":{"id":"DayNarrowSat","value":"C"},"DayNarrowSun":{"id":"DayNarrowSun","value":"P"},"DayNarrowThu":{"id":"DayNarrowThu","value":"P"},"DayNarrowTue":{"id":"DayNarrowTue","value":"S"},"DayNarrowWed":{"id":"DayNarrowWed","value":"Ç"},"DayPeriod0":{"id":"DayPeriod0","value":"Öğleden Önce"},"DayPeriod1":{"id":"DayPeriod1","value":"Öğleden Sonra"},"DayWideFri":{"id":"DayWideFri","value":"Cuma"},"DayWideMon":{"id":"DayWideMon","value":"Pazartesi"},"DayWideSat":{"id":"DayWideSat","value":"Cumartesi"},"DayWideSun":{"id":"DayWideSun","value":"Pazar"},"DayWideThu":{"id":"DayWideThu","value":"Perşembe"},"DayWideTue":{"id":"DayWideTue","value":"Salı"},"DayWideWed":{"id":"DayWideWed","value":"Çarşamba"},"Days":{"id":"Days","value":"Gün "},"DaysOverdue":{"id":"DaysOverdue","value":"tarihi {0} gün geçti"},"DaysRemaining":{"id":"DaysRemaining","value":"{0} gün kaldı"},"Default":{"id":"Default","value":"Varsayılan"},"Delete":{"id":"Delete","value":"Sil"},"DeleteEvent":{"id":"DeleteEvent","value":"Olayı Sil"},"Device":{"id":"Device","value":"Aygıt"},"Dirty":{"id":"Dirty","value":"Satır değişti"},"DiscretionaryTimeOff":{"id":"DiscretionaryTimeOff","value":"İsteğe bağlı izin"},"DistributeHoriz":{"id":"DistributeHoriz","value":"Yatay olarak dağıt"},"Document":{"id":"Document","value":"Belge"},"DoesNotContain":{"id":"DoesNotContain","value":"Şunu İçermez"},"DoesNotEndWith":{"id":"DoesNotEndWith","value":"Şununla bitmez"},"DoesNotEqual":{"id":"DoesNotEqual","value":"Şuna eşit değil"},"DoesNotStartWith":{"id":"DoesNotStartWith","value":"Şununla başlamaz"},"Down":{"id":"Down","value":"Aşağı"},"Download":{"id":"Download","value":"İndir"},"Drilldown":{"id":"Drilldown","value":"Detaya git"},"Drillup":{"id":"Drillup","value":"Detaydan çık"},"Dropdown":{"id":"Dropdown","value":"Açılır"},"DropdownTriggerButton":{"id":"DropdownTriggerButton","value":"Açılır listeyi açmak için tıklayın"},"Duplicate":{"id":"Duplicate","value":"Yinelenen"},"Duration":{"id":"Duration","value":"Süre"},"Dutch":{"id":"Dutch","value":"Felemenkçe"},"EarlyOrEquals":{"id":"EarlyOrEquals","value":"Daha önce Veya eşit"},"EarlyOrUntil":{"id":"EarlyOrUntil","value":"Daha önce Veya buna kadar"},"EarlyThan":{"id":"EarlyThan","value":"Daha önce"},"Edit":{"id":"Edit","value":"Düzenle"},"EitherSelectedOrNotSelected":{"id":"EitherSelectedOrNotSelected","value":"Seçili veya seçili değil"},"EmailValidation":{"id":"EmailValidation","value":"E-posta adresi geçerli değil"},"Emerald":{"id":"Emerald","value":"Zümrüt"},"EndsWith":{"id":"EndsWith","value":"Şununla Biter"},"English":{"id":"English","value":"İngilizce (Amerika Birleşik Devletleri)"},"EnterComments":{"id":"EnterComments","value":"Buraya yorum girin..."},"Equals":{"id":"Equals","value":"Şuna Eşit"},"Error":{"id":"Error","value":"Hata"},"ErrorAllowedTypes":{"id":"ErrorAllowedTypes","value":"Dosya türüne izin verilmiyor"},"ErrorMaxFileSize":{"id":"ErrorMaxFileSize","value":"Dosya boyut sınırı aşıldı"},"ErrorMaxFiles":{"id":"ErrorMaxFiles","value":"Maksimum dosya sayısından ({n}) fazla dosya yüklenemez."},"ErrorMaxFilesInProcess":{"id":"ErrorMaxFilesInProcess","value":"Maksimum izin verilen dosya sınırı aşıldı"},"ErrorOnPage":{"id":"ErrorOnPage","value":"Sayfada hata mesajları"},"Estonian":{"id":"Estonian","value":"Estonca"},"Event":{"id":"Event","value":"Olay"},"EventType":{"id":"EventType","value":"Olay türü"},"ExampleData":{"id":"ExampleData","value":"Örnek veri"},"ExampleLabel":{"id":"ExampleLabel","value":"Örnek etiket"},"ExamplePlaceholder":{"id":"ExamplePlaceholder","value":"Örnek yer tutucu"},"ExitFullView":{"id":"ExitFullView","value":"Tam görünümden çık"},"Expand":{"id":"Expand","value":"Genişlet"},"ExpandAppTray":{"id":"ExpandAppTray","value":"Uygulama tepsisini genişlet"},"ExpandCollapse":{"id":"ExpandCollapse","value":"Genişlet / Daralt"},"Export":{"id":"Export","value":"Dışarı Aktar"},"ExportAsSpreadsheet":{"id":"ExportAsSpreadsheet","value":"Elektronik tablo olarak dışarı aktar"},"ExportToCsv":{"id":"ExportToCsv","value":"CSV'ye aktar"},"ExportToExcel":{"id":"ExportToExcel","value":"Excel'e Aktar"},"ExtraSmall":{"id":"ExtraSmall","value":"Ekstra küçük"},"Favorite":{"id":"Favorite","value":"Sık Kullanılan"},"FieldFilter":{"id":"FieldFilter","value":"Alan filtresi"},"FileUpload":{"id":"FileUpload","value":"Dosya yükleme. Bir dosyaya gözatmak için enter tuşuna basın"},"Filter":{"id":"Filter","value":"Filtrele"},"Finnish":{"id":"Finnish","value":"Fince"},"FirstPage":{"id":"FirstPage","value":"İlk sayfa"},"Folder":{"id":"Folder","value":"Klasör"},"FontPickerHeader":{"id":"FontPickerHeader","value":"Üstbilgi {0}"},"FontPickerNormal":{"id":"FontPickerNormal","value":"Normal metin"},"FontPickerStyle":{"id":"FontPickerStyle","value":"Yazı tipi stili"},"Forms":{"id":"Forms","value":"Biçimler"},"French":{"id":"French","value":"Fransızca"},"From":{"id":"From","value":"Başlangıç"},"FullView":{"id":"FullView","value":"Tam görünüm"},"German":{"id":"German","value":"Almanca"},"Go":{"id":"Go","value":"Git"},"GoBack":{"id":"GoBack","value":"Geri git"},"GoDown":{"id":"GoDown","value":"Aşağı git"},"GoForward":{"id":"GoForward","value":"İleri git"},"GoUp":{"id":"GoUp","value":"Yukarı Git"},"Graphite":{"id":"Graphite","value":"Grafit"},"GreaterOrEquals":{"id":"GreaterOrEquals","value":"Şundan daha fazla veya eşit"},"GreaterThan":{"id":"GreaterThan","value":"Şundan büyük:"},"Grid":{"id":"Grid","value":"Kılavuz"},"Group":{"id":"Group","value":"Grup"},"Groups":{"id":"Groups","value":"Gruplar"},"GroupsPerPage":{"id":"GroupsPerPage","value":"sayfa başına {0} grup"},"HeadingFour":{"id":"HeadingFour","value":"Başlık dört"},"HeadingThree":{"id":"HeadingThree","value":"Başlık üç"},"Hebrew":{"id":"Hebrew","value":"İbranice"},"Hide":{"id":"Hide","value":"Gizle"},"HighContrast":{"id":"HighContrast","value":"Yüksek kontrast"},"Highest":{"id":"Highest","value":"En Yüksek"},"Highlight":{"id":"Highlight","value":"Vurgula"},"Hindi":{"id":"Hindi","value":"Hintçe"},"Home":{"id":"Home","value":"Giriş"},"Hour":{"id":"Hour","value":"Saat"},"Hours":{"id":"Hours","value":"Saat"},"HtmlView":{"id":"HtmlView","value":"Html görünümü"},"Hungarian":{"id":"Hungarian","value":"Macarca"},"Id":{"id":"Id","value":"Kimlik"},"Image":{"id":"Image","value":"Görüntü"},"Import":{"id":"Import","value":"İçeri Aktar"},"InProgress":{"id":"In Progress","value":"Devam ediyor"},"InRange":{"id":"InRange","value":"Aralıkta"},"Indonesian":{"id":"Indonesian","value":"Endonezce"},"Info":{"id":"Info","value":"Bilgi"},"InfoOnPage":{"id":"InfoOnPage","value":"Sayfada bilgi mesajları"},"Insert":{"id":"Insert","value":"Ekle"},"InsertAnchor":{"id":"InsertAnchor","value":"Bağlayıcı ekle"},"InsertHyperlink":{"id":"InsertHyperlink","value":"Köprü ekle"},"InsertImage":{"id":"InsertImage","value":"Görüntü ekle"},"InsertLink":{"id":"InsertLink","value":"Bağlantı ekle"},"InsertUrl":{"id":"InsertUrl","value":"Url ekle"},"InvalidDate":{"id":"InvalidDate","value":"Geçersiz tarih"},"InvalidDateTime":{"id":"InvalidDateTime","value":"Geçersiz tarih veya saat"},"InvalidTime":{"id":"InvalidTime","value":"Geçersiz zaman"},"Inventory":{"id":"Inventory","value":"Stok"},"IsEmpty":{"id":"IsEmpty","value":"Boş"},"IsNotEmpty":{"id":"IsNotEmpty","value":"Boş değil"},"Italic":{"id":"Italic","value":"İtalik"},"ItemsSelected":{"id":"ItemsSelected","value":"Seçilen öğeler"},"Japanese":{"id":"Japanese","value":"Japonca"},"JustifyCenter":{"id":"JustifyCenter","value":"Ortala"},"JustifyLeft":{"id":"JustifyLeft","value":"Sola hizala"},"JustifyRight":{"id":"JustifyRight","value":"Sağa hizala"},"Keyword":{"id":"Keyword","value":"Anahtar Sözcük"},"Korean":{"id":"Korean","value":"Korece"},"Language":{"id":"Language","value":"Dil"},"Large":{"id":"Large","value":"Büyük"},"LastPage":{"id":"LastPage","value":"Son sayfa"},"LaterOrEquals":{"id":"LaterOrEquals","value":"Daha sonra veya eşit"},"LaterOrOn":{"id":"LaterOrOn","value":"Daha sonra veya tam üzerinde"},"LaterThan":{"id":"LaterThan","value":"Daha sonra"},"Latvian":{"id":"Latvian","value":"Letonca"},"Launch":{"id":"Launch","value":"Başlat"},"Left":{"id":"Left","value":"Sol"},"Legend":{"id":"Legend","value":"Açıklama"},"LessOrEquals":{"id":"LessOrEquals","value":"Şundan daha az veya eşit"},"LessThan":{"id":"LessThan","value":"Şundan küçük:"},"Light":{"id":"Light","value":"Aydınlık"},"Link":{"id":"Link","value":"Bağlantı"},"LineChart":{"id":"LineChart","value":"Çizgi Grafik"},"Lithuanian":{"id":"Lithuanian","value":"Litvanca"},"Load":{"id":"Load","value":"Yükle"},"Loading":{"id":"Loading","value":"Yükleniyor"},"Locale":{"id":"Locale","value":"Yerel Ayarlar"},"Locked":{"id":"Locked","value":"Kilitli"},"Logout":{"id":"Logout","value":"Oturumu kapat"},"Lookup":{"id":"Lookup","value":"Arama"},"LookupTriggerButton":{"id":"LookupTriggerButton","value":"Arama tetikleyici"},"Lowest":{"id":"Lowest","value":"En Düşük"},"Mail":{"id":"Mail","value":"Posta"},"Malay":{"id":"Malay","value":"Malayca"},"MapPin":{"id":"MapPin","value":"Sabitle"},"Maximize":{"id":"Maximize","value":"Ekranı Kapla"},"Median":{"id":"Median","value":"Medyan"},"Medium":{"id":"Medium","value":"Orta"},"Menu":{"id":"Menu","value":"Menü"},"MenuGroup":{"id":"MenuGroup","value":"{0} öğe içeren menü grubu"},"MillionsAbbrev":{"id":"MillionsAbbrev","value":"{0}M"},"MingleShare":{"id":"MingleShare","value":"Ming.le ile Paylaş"},"Minimize":{"id":"Minimize","value":"Simge Durumuna Küçült"},"Minus":{"id":"Minus","value":"Eksi"},"Minute":{"id":"Minute","value":"Dakika"},"Minutes":{"id":"Minutes","value":"Dakika"},"Mobile":{"id":"Mobile","value":"Mobil"},"Mode":{"id":"Mode","value":"Mod"},"Modes":{"id":"Modes","value":"Modlar"},"Month":{"id":"Month","value":"Ay"},"MonthAbbreviatedApr":{"id":"MonthAbbreviatedApr","value":"Nis"},"MonthAbbreviatedAug":{"id":"MonthAbbreviatedAug","value":"Ağu"},"MonthAbbreviatedDec":{"id":"MonthAbbreviatedDec","value":"Ara"},"MonthAbbreviatedFeb":{"id":"MonthAbbreviatedFeb","value":"Şub"},"MonthAbbreviatedJan":{"id":"MonthAbbreviatedJan","value":"Oca"},"MonthAbbreviatedJuly":{"id":"MonthAbbreviatedJuly","value":"Tem"},"MonthAbbreviatedJune":{"id":"MonthAbbreviatedJune","value":"Haz"},"MonthAbbreviatedLowerCaseApr":{"id":"MonthAbbreviatedApr","value":"Nis"},"MonthAbbreviatedLowerCaseDec":{"id":"MonthAbbreviatedDec","value":"Ara"},"MonthAbbreviatedLowerCaseFeb":{"id":"MonthAbbreviatedFeb","value":"Şub"},"MonthAbbreviatedLowerCaseJan":{"id":"MonthAbbreviatedJan","value":"Oca"},"MonthAbbreviatedLowerCaseJuly":{"id":"MonthAbbreviatedJuly","value":"Tem"},"MonthAbbreviatedLowerCaseJune":{"id":"MonthAbbreviatedJune","value":"Haz"},"MonthAbbreviatedLowerCaseLowerCaseAug":{"id":"MonthAbbreviatedAug","value":"Ağu"},"MonthAbbreviatedLowerCaseMar":{"id":"MonthAbbreviatedMar","value":"Mar"},"MonthAbbreviatedLowerCaseMay":{"id":"MonthAbbreviatedMay","value":"Mayıs"},"MonthAbbreviatedLowerCaseNov":{"id":"MonthAbbreviatedNov","value":"Kas"},"MonthAbbreviatedLowerCaseOct":{"id":"MonthAbbreviatedOct","value":"Eki"},"MonthAbbreviatedLowerCaseSep":{"id":"MonthAbbreviatedSep","value":"Eyl"},"MonthAbbreviatedMar":{"id":"MonthAbbreviatedMar","value":"Mar"},"MonthAbbreviatedMay":{"id":"MonthAbbreviatedMay","value":"Mayıs"},"MonthAbbreviatedNov":{"id":"MonthAbbreviatedNov","value":"Kas"},"MonthAbbreviatedOct":{"id":"MonthAbbreviatedOct","value":"Eki"},"MonthAbbreviatedSep":{"id":"MonthAbbreviatedSep","value":"Eyl"},"MonthWideApr":{"id":"MonthWideApr","value":"Nisan"},"MonthWideAug":{"id":"MonthWideAug","value":"Ağustos"},"MonthWideDec":{"id":"MonthWideDec","value":"Aralık"},"MonthWideFeb":{"id":"MonthWideFeb","value":"Şubat"},"MonthWideJan":{"id":"MonthWideJan","value":"Ocak"},"MonthWideJuly":{"id":"MonthWideJuly","value":"Temmuz"},"MonthWideJune":{"id":"MonthWideJune","value":"Haziran"},"MonthWideLowerCaseApr":{"id":"MonthWideApr","value":"nisan"},"MonthWideLowerCaseAug":{"id":"MonthWideAug","value":"ağustos"},"MonthWideLowerCaseDec":{"id":"MonthWideDec","value":"aralık"},"MonthWideLowerCaseFeb":{"id":"MonthWideFeb","value":"şubat"},"MonthWideLowerCaseJan":{"id":"MonthWideJan","value":"ocak"},"MonthWideLowerCaseJuly":{"id":"MonthWideJuly","value":"temmuz"},"MonthWideLowerCaseJune":{"id":"MonthWideJune","value":"haziran"},"MonthWideLowerCaseMar":{"id":"MonthWideMar","value":"mart"},"MonthWideLowerCaseMay":{"id":"MonthWideMay","value":"mayıs"},"MonthWideLowerCaseNov":{"id":"MonthWideNov","value":"kasım"},"MonthWideLowerCaseOct":{"id":"MonthWideOct","value":"ekim"},"MonthWideLowerCaseSep":{"id":"MonthWideSep","value":"eylül"},"MonthWideMar":{"id":"MonthWideMar","value":"Mart"},"MonthWideMay":{"id":"MonthWideMay","value":"Mayıs"},"MonthWideNov":{"id":"MonthWideNov","value":"Kasım"},"MonthWideOct":{"id":"MonthWideOct","value":"Ekim"},"MonthWideSep":{"id":"MonthWideSep","value":"Eylül"},"More":{"id":"More","value":"Daha fazla"},"MoreActions":{"id":"MoreActions","value":"Daha fazla eylem"},"MoveToLeft":{"id":"MoveToLeft","value":"Sola taşı"},"MoveToRight":{"id":"MoveToRight","value":"Sağa taşı"},"MsgDirty":{"id":"MsgDirty","value":", Düzenlenmiş"},"New":{"id":"New","value":"Yeni "},"NewDarkTheme":{"id":"NewDarkTheme","value":"Yeni karanlık"},"NewDocument":{"id":"NewDocument","value":"Yeni belge"},"NewEvent":{"id":"NewEvent","value":"Yeni olay"},"NewEventDetails":{"id":"NewEventDetails","value":"Yeni olay ayrıntıları"},"NewHighContrastTheme":{"id":"NewHighContrastTheme","value":"Yeni yüksek kontrast"},"NewItem":{"id":"NewItem","value":"Yeni öğe"},"NewLightTheme":{"id":"NewLightTheme","value":"Yeni aydınlık"},"NewRow":{"id":"New","value":"Yeni "},"NewWindow":{"id":"NewWindow","value":"Yeni pencere"},"Next":{"id":"Next","value":"Sonraki"},"NextMonth":{"id":"NextMonth","value":"Sonraki ay"},"NextPage":{"id":"NextPage","value":"Sonraki sayfa"},"NextRecord":{"id":"NextRecord","value":"Sonraki kayıt"},"NextWeek":{"id":"NextWeek","value":"Sonraki hafta"},"NextYear":{"id":"NextYear","value":"Sonraki yıl"},"No":{"id":"No","value":"Hayır"},"NoCommentsEntered":{"id":"NoCommentsEntered","value":"Yorum girilmedi"},"NoData":{"id":"NoData","value":"Veri yok"},"NoDataFilter":{"id":"NoDataFilter","value":"Mevcut veri yok, daha fazla sonuç görmek için yeni bir filtre seçimi yapın."},"NoDataList":{"id":"NoDataList","value":"Mevcut veri yok, daha fazla sonuç görmek için yukarıdaki listede bir seçim yapın."},"NoResults":{"id":"NoResults","value":"Sonuç yok"},"NoResultsFound":{"id":"NoResultsFound","value":"Sonuç bulunamadı"},"NoRecordSelected":{"id":"NoRecordSelected","value":"0 kayıt seçildi"},"NoTitle":{"id":"NoTitle","value":"(Başlık yok)"},"None":{"id":"None","value":"Hiçbiri"},"Normal":{"id":"Normal","value":"Normal"},"Norwegian":{"id":"Norwegian","value":"Norveççe"},"NotSelected":{"id":"NotSelected","value":"Seçilmedi"},"Notes":{"id":"Notes","value":"Notlar"},"NumberList":{"id":"NumberList","value":"Sayı listesi"},"Ok":{"id":"Ok","value":"Tamam"},"OperatingSystem":{"id":"OperatingSystem","value":"İşletim sistemi"},"OrderedList":{"id":"OrderedList","value":"Numaralı listeyi ekle/kaldır"},"Page":{"id":"Page","value":"sayfa "},"PageOf":{"id":"PageOf","value":"Sayfa {0} / {1}"},"PageOn":{"id":"PageOn","value":"Şu anda bu sayfadasınız: "},"Pagination":{"id":"Pagination","value":"Sayfa Numaralama"},"PaidTimeOff":{"id":"PaidTimeOff","value":"Ücretli izin"},"PasswordConfirmValidation":{"id":"PasswordConfirmValidation","value":"Parola eşleşmelidir"},"PasswordValidation":{"id":"PasswordValidation","value":"<strong>Parola:</strong><br>En az 10 karakter uzunluğunda olmalıdır<br>En az bir büyük harf karakteri içermelidir<br>En az bir küçük harf karakteri içermelidir<br>Bir özel karakter içermelidir<br>Kullanıcı adınızı içermemelidir<br>Daha Önce kullanılan bir parola olamaz<br>"},"Paste":{"id":"Paste","value":"Yapıştır"},"Peak":{"id":"Peak","value":"Tepe"},"Pending":{"id":"Pending","value":"Bekliyor"},"Period":{"id":"Period","value":"Dönem"},"Personalization":{"id":"Personalization","value":"Kişiselleştirme"},"PersonalizeColumns":{"id":"PersonalizeColumns","value":"Sütunları kişiselleştir"},"Plan":{"id":"Plan","value":"Plan"},"Platform":{"id":"Platform","value":"Platform"},"Polish":{"id":"Polish","value":"Lehçe"},"Portuguese":{"id":"Portuguese","value":"Portekizce"},"PressDown":{"id":"PressDown","value":"Seçmek için aşağı oka basın"},"PressShiftF10":{"id":"PressShiftF10","value":"İçerik menüsünü açmak için Shift+F10 tuşuna basın."},"Previous":{"id":"Previous","value":"Önceki"},"PreviousMonth":{"id":"PreviousMonth","value":"Önceki ay"},"PreviousPage":{"id":"PreviousPage","value":"Önceki sayfa"},"PreviousRecord":{"id":"PreviousRecord","value":"Önceki kayıt"},"PreviousWeek":{"id":"PreviousWeek","value":"Önceki hafta"},"PreviousYear":{"id":"PreviousYear","value":"Önceki yıl"},"Print":{"id":"Print","value":"Yazdır"},"Range":{"id":"Range","value":"Aralık"},"RecordsPerPage":{"id":"RecordsPerPage","value":"sayfa başına {0} kayıt"},"RecordsPerPageNoToken":{"id":"RecordsPerPageNoToken","value":"Sayfa başına kayıt"},"RecordSelected":{"id":"RecordSelected","value":"{0} kayıt seçildi"},"RecordsSelected":{"id":"RecordsSelected","value":"{0} kayıt seçildi"},"Redo":{"id":"Redo","value":"Yinele"},"Refresh":{"id":"Refresh","value":"Yenile"},"ReorderRows":{"id":"ReorderRows","value":"Satırları yeniden düzenle"},"RequestTimeOff":{"id":"RequestTimeOff","value":"İzin iste"},"Required":{"id":"Required","value":"Gerekli"},"Reset":{"id":"Reset","value":"Sıfırla"},"ResetDefault":{"id":"ResetDefault","value":"Varsayılana sıfırla"},"Result":{"id":"Result","value":"({0} sonuç)"},"ResultOf":{"id":"ResultOf","value":"{0} / {1} sonuç"},"Results":{"id":"Results","value":"({0} sonuç)"},"ResultsOf":{"id":"ResultsOf","value":"{0} / {1} sonuç"},"Right":{"id":"Right","value":"Sağ"},"RightAlign":{"id":"RightAlign","value":"Sağa hizala"},"Roles":{"id":"Roles","value":"Roller"},"Romanian":{"id":"Romanian","value":"Rumence"},"RowHeight":{"id":"RowHeight","value":"Satır Yüksekliği"},"Ruby":{"id":"Ruby","value":"Yakut"},"RunFilter":{"id":"RunFilter","value":"Filtreyi çalıştır"},"Russian":{"id":"Russian","value":"Rusça"},"SameWindow":{"id":"SameWindow","value":"Aynı pencere"},"Save":{"id":"Save","value":"Kaydet"},"SaveCurrentView":{"id":"SaveCurrentView","value":"Mevcut görünümü kaydet"},"SavedViews":{"id":"SavedViews","value":"Kaydedilen görünümler"},"Schedule":{"id":"Schedule","value":"Program"},"Search":{"id":"Search","value":"Ara"},"SearchColumnName":{"id":"SearchColumnName","value":"Bir sütun adı ara"},"SearchFolder":{"id":"SearchFolder","value":"Klasörde ara"},"SearchList":{"id":"SearchList","value":"Listeyi ara"},"Second":{"id":"Second","value":"Saniye"},"Seconds":{"id":"Seconds","value":"Saniye"},"Select":{"id":"Select","value":"Seç"},"SelectAll":{"id":"SelectAll","value":"Tümünü seç"},"SelectDay":{"id":"SelectDay","value":"Bir gün seç"},"Selected":{"id":"Selected","value":"Seçilen"},"SelectedOptions":{"id":"SelectedOptions","value":"Seçilen seçenekler"},"Selection":{"id":"Selection","value":"Seçim"},"Send":{"id":"Send","value":"Gönder"},"SetTime":{"id":"SetTime","value":"Saati ayarla"},"Settings":{"id":"Settings","value":"Ayarlar"},"Short":{"id":"Short","value":"Kısa"},"Show":{"id":"Show","value":"Göster"},"ShowEvent":{"id":"ShowEvent","value":"Olayı göster"},"ShowFilterRow":{"id":"ShowFilterRow","value":"Filtre satırını göster"},"ShowLess":{"id":"ShowLess","value":"Daha az göster"},"ShowMore":{"id":"ShowMore","value":"Daha fazla göster"},"SickTime":{"id":"SickTime","value":"Hastalık süresi"},"SkipToMain":{"id":"SkipToMain","value":"Ana içeriğe atla"},"Slate":{"id":"Slate","value":"Arduvaz"},"SlideOf":{"id":"SlideOf","value":"Slayt {0} / {1}"},"SliderHandle":{"id":"SliderHandle","value":"Şunun için tutamaç:"},"SliderMaximumHandle":{"id":"SliderMaximumHandle","value":"Şunun için maksimum tutamaç aralığı:"},"SliderMinimumHandle":{"id":"SliderMinimumHandle","value":"Şunun için minimum tutamaç aralığı:"},"SlidesOf":{"id":"SlidesOf","value":"Slayt {0} ve {1} / {2}"},"Slovak":{"id":"Slovak","value":"Slovakça"},"Slovenian":{"id":"Slovenian","value":"Slovence"},"Small":{"id":"Small","value":"Küçük"},"SortAtoZ":{"id":"SortAtoZ","value":"Artan şekilde sırala"},"SortDown":{"id":"SortDown","value":"Aşağı sırala"},"SortUp":{"id":"SortUp","value":"Yukarı Sırala"},"SortZtoA":{"id":"SortZtoA","value":"Azalan şekilde sırala"},"Spanish":{"id":"Spanish","value":"İspanyolca"},"SplitterCollapseButton":{"id":"SplitterCollapseButton","value":"Ayırıcıyı daralt"},"SplitterDragHandle":{"id":"SplitterDragHandle","value":"Ayarlamak için sürükleyin"},"StartsWith":{"id":"StartsWith","value":"Şununla Başlar"},"Status":{"id":"Status","value":"Durum"},"StepsCompleted":{"id":"StepsCompleted","value":"{0} / {1} adım tamamlandı"},"StrikeThrough":{"id":"StrikeThrough","value":"Üstü çizili"},"String":{"id":"String","value":"Dize"},"Strings":{"id":"Strings","value":"Dizeler"},"Subject":{"id":"Subject","value":"Konu"},"Submit":{"id":"Submit","value":"Gönder"},"Subscript":{"id":"Subscript","value":"Alt Simge"},"Subtle":{"id":"Subtle","value":"İnce"},"Superscript":{"id":"Superscript","value":"Üst Simge"},"Swedish":{"id":"Swedish","value":"İsveççe"},"Tabs":{"id":"Tabs","value":"Sekmeler..."},"Tack":{"id":"Tack","value":"Sabitle"},"Tagalog":{"id":"Tagalog","value":"Tagalogca"},"Tall":{"id":"Tall","value":"Uzun"},"Target":{"id":"Target","value":"Hedef"},"TeamEvent":{"id":"TeamEvent","value":"Ekip olayı"},"TestLocaleDefaults":{"id":"TestLocaleDefaults","value":"Yerel ayar varsayılanlarını test et"},"TextBtnCancel":{"id":"TextBtnCancel","value":"Bu dosya yüklemesini iptal et"},"TextBtnCloseError":{"id":"TextBtnCloseError","value":"Bu hatayı kapat"},"TextBtnRemove":{"id":"TextBtnRemove","value":"Bu hatayı kapat"},"TextColor":{"id":"TextColor","value":"Metin rengi"},"TextDropArea":{"id":"DropArea","value":"Yüklenecek dosyaları sürükleyin ve bırakın"},"TextDropAreaWithBrowse":{"id":"TextDropAreaWithBrowse","value":"Yüklemek için buraya sürükleyip bırakın veya <span class=\"hyperlink\">dosya yükleme</span>"},"TextDropAreaWithBrowseLink":{"id":"TextDropAreaWithBrowse","value":"Buraya sürükleyip bırakın veya {browseLink}"},"Thai":{"id":"Thai","value":"Tayca"},"Theme":{"id":"Theme","value":"Tema"},"ThousandsAbbrev":{"id":"ThousandsAbbrev","value":"{0}k"},"Time":{"id":"Time","value":"Saat"},"TimepickerPopup":{"id":"TimepickerPopup","value":"Saat seçici açılır penceresi"},"TimepickerTriggerButton":{"id":"TimepickerTriggerButton","value":"Saat seçiciyi açmak için tıklayın"},"Timer":{"id":"Timer","value":"Zamanlayıcı"},"To":{"id":"To","value":"Bitiş"},"Today":{"id":"Today","value":"Bugün"},"ToggleBold":{"id":"ToggleBold","value":"Kalın metni değiştir"},"ToggleH3":{"id":"ToggleH3","value":"Başlık 3'ü değiştir"},"ToggleH4":{"id":"ToggleH4","value":"Başlık 4'ü değiştir"},"ToggleItalic":{"id":"ToggleItalic","value":"İtalik metni değiştir"},"ToggleUnderline":{"id":"ToggleUnderline","value":"Altı çizili metni değiştir"},"Toolbar":{"id":"Toolbar","value":"Araç Çubuğu"},"TopAlign":{"id":"TopAlign","value":"Üste hizala"},"Total":{"id":"Total","value":"Toplam"},"Totals":{"id":"Totals","value":"Toplam"},"TreeCollapse":{"id":"TreeCollapse","value":"Ağacı daralt"},"TreeExpand":{"id":"TreeExpand","value":"Ağacı genişlet"},"TrillionsAbbrev":{"id":"TrillionsAbbrev","value":"{0}T"},"Turkish":{"id":"Turkish","value":"Türkçe"},"Turquoise":{"id":"Turquoise","value":"Turkuaz"},"Type":{"id":"Type","value":"Tür"},"TypeToFilter":{"id":"TypeToFilter","value":"Filtrelemek için yazın"},"Ukrainian":{"id":"Ukrainian","value":"Ukraynaca"},"UnavailableDate":{"id":"UnavailableDate","value":"Uygun olmayan tarih"},"Underline":{"id":"Underline","value":"Altı Çizili"},"Undo":{"id":"Undo","value":"Geri Al"},"Unlocked":{"id":"Unlocked","value":"Kilidi Açık"},"UnorderedList":{"id":"UnorderedList","value":"Madde işaretli listeyi ekle/kaldır"},"Unsupported":{"id":"Unsupported","value":"Bu içerik mevcut değil, çünkü geçerli tarayıcı sürümünüzde desteklenmeyen özellikler kullanıyor."},"Up":{"id":"Up","value":"Yukarı"},"UpComing":{"id":"UpComing","value":"Yakında Gelenler"},"UpComingEvents":{"id":"UpComingEvents","value":"Yaklaşan olaylar"},"UpComingTimeOff":{"id":"UpComingTimeOff","value":"Yaklaşan izin"},"UpliftDarkTheme":{"id":"UpliftDarkTheme","value":"Karanlığı artır"},"UpliftHighContrastTheme":{"id":"UpliftHighContrastTheme","value":"Yüksek kontrastı artır"},"UpliftLightTheme":{"id":"UpliftLightTheme","value":"Aydınlığı artır"},"Upload":{"id":"Upload","value":"Karşıya Yükle"},"UploadDropArea":{"id":"UploadDropArea","value":"Dosyaları yüklemek için buraya sürükleyip bırakın"},"UploadErrorMaxFiles":{"id":"UploadErrorMaxFiles","value":"<em>Hata</em> Maksimum dosya sayısından ({maxFiles}) fazla dosya yüklenemez"},"UploadErrorMaxFilesInProgress":{"id":"UploadErrorMaxFiles","value":"<em>Hata</em> Maksimum izin verilen dosya aşıldı"},"UploadErrorMaxFileSize":{"id":"UploadErrorMaxFileSize","value":"<em>Hata</em> Dosya boyut sınırı aşıldı"},"UploadErrorAcceptedFileType":{"id":"UploadErrorAcceptedFileType","value":"<em>Hata</em> Dosya türüne izin verilmiyor"},"UploadErrorUrl":{"id":"UploadErrorUrl","value":"<em>Hata</em> Url bulunamadı"},"UploadErrorXHRHeaders":{"id":"UploadErrorUrl","value":"<em>Hata</em> İstek Başlıkları geçerli bir JSON dizesi olmalıdır"},"UploadLink":{"id":"UploadLink","value":"dosyaları yükle"},"UploadCancel":{"id":"UploadCancel","value":"Bu dosya yüklemesini iptal et"},"UploadCancelAll":{"id":"UploadCancelAll","value":"Tümünü iptal et"},"UploadDismissError":{"id":"UploadDismissError","value":"Bu hatayı kapat"},"UploadProgressLabel":{"id":"UploadProgressLabel","value":"{file-name}, {loaded} / {size} yükledi (%{percent})"},"UploadRemoveFile":{"id":"UploadRemoveFile","value":"Bu dosyayı kaldır"},"UploadStart":{"id":"UploadStart","value":"Bu dosyayı yüklemeye başla"},"Url":{"id":"Url","value":"Url"},"UseArrow":{"id":"UseArrow","value":". Seçmek için ok tuşlarını kullanın."},"UseEnter":{"id":"UseEnter","value":". Arama yapmak için enter tuşunu veya aşağı oku kullanın."},"User":{"id":"User","value":"Kullanıcı"},"UserProfile":{"id":"UserProfile","value":"Kullanıcı Profili"},"Variant":{"id":"Variant","value":"Değişken"},"Version":{"id":"Version","value":"IDS sürümü"},"Versions":{"id":"Versions","value":"Sürümler"},"VerticalMiddleAlign":{"id":"VerticalMiddleAlign","value":"Dikey hizalama orta"},"Vibrant":{"id":"Vibrant","value":"Canlı"},"Vietnamese":{"id":"Vietnamese","value":"Vietnamca"},"ViewSource":{"id":"ViewSource","value":"Kaynağı görüntüle"},"ViewVisual":{"id":"ViewVisual","value":"Görseli görüntüle"},"Week":{"id":"Week","value":"Hafta"},"WeekNumber":{"id":"WeekNumber","value":"H#"},"Year":{"id":"Year","value":"Yıl"},"Yes":{"id":"Yes","value":"Evet"}}